{"name":"Registro de un usuario nuevo","id":"realizar-el-ingreso-utest.com-y-luego-proceder;registro-de-un-usuario-nuevo","testSteps":[{"number":1,"description":"Dado cualquier persona que desea hacer parte de la comunidad Utest.com y da clic en el boton \"join today\"","duration":5,"startTime":"2021-02-21T17:34:27.387-05:00[America/Bogota]","result":"PENDING","precondition":false,"level":0},{"number":2,"description":"Cuando En cualquier momento ya que es una pagina para aprender acerca del testing y tranajar freelance","duration":14,"startTime":"2021-02-21T17:34:27.401-05:00[America/Bogota]","result":"IGNORED","precondition":false,"level":0},{"number":3,"description":"Entonces Esta debe cargar el formulario y realizar el registro de manera automatica","duration":5,"startTime":"2021-02-21T17:34:27.421-05:00[America/Bogota]","result":"IGNORED","precondition":false,"level":0}],"userStory":{"id":"realizar-el-ingreso-utest.com-y-luego-proceder","storyName":"Realizar el ingreso Utest.com y luego proceder","path":"src/test/resources/Features/Ejemplo.feature","narrative":"  a hacer clic en Join Today y finalmente realizar el diligenciamiento del formulario\n  para la creacion de un nuevo usuario.","type":"feature"},"featureTag":{"name":"Features/Realizar el ingreso Utest.com y luego proceder","type":"feature","displayName":"Features/Realizar el ingreso Utest.com y luego proceder"},"title":"Registro de un usuario nuevo","tags":[{"name":"Realizar el ingreso Utest.com y luego proceder","type":"feature","displayName":"Realizar el ingreso Utest.com y luego proceder"}],"startTime":"2021-02-21T17:34:27.351-05:00[America/Bogota]","duration":77,"projectKey":"","annotatedResult":"PENDING","isManualTestingUpToDate":false,"manual":false,"testSource":"Cucumber","result":"PENDING"}